apichainer/__init__.py
apichainer/main.py
apichainer-0.1.0.dist-info/LICENSE
apichainer-0.1.0.dist-info/METADATA
apichainer-0.1.0.dist-info/WHEEL
apichainer-0.1.0.dist-info/RECORD
