Metadata-Version: 2.3
Name: apichainer
Version: 0.1.0
Summary: A declarative Python library for building chained HTTP request workflows using a fluent interface.
License: MIT
Keywords: api,requests,chain,workflow,automation,aiohttp,async
Author: David AF.
Author-email: knot1025@gmail.com
Requires-Python: >=3.9
Classifier: Development Status :: 4 - Beta
Classifier: Intended Audience :: Developers
Classifier: License :: OSI Approved :: MIT License
Classifier: Programming Language :: Python :: 3
Classifier: Programming Language :: Python :: 3.9
Classifier: Programming Language :: Python :: 3.10
Classifier: Programming Language :: Python :: 3.11
Classifier: Programming Language :: Python :: 3.12
Classifier: Operating System :: OS Independent
Classifier: Topic :: Internet :: WWW/HTTP
Classifier: Topic :: Software Development :: Libraries :: Python Modules
Provides-Extra: dev
Requires-Dist: aiofiles (>=23.2.1,<24.0.0)
Requires-Dist: aiohttp (>=3.9.5,<4.0.0)
Requires-Dist: black (>=23.0.0,<24.0.0) ; extra == "dev"
Requires-Dist: flake8 (>=6.0.0,<7.0.0) ; extra == "dev"
Requires-Dist: isort (>=5.12.0,<6.0.0) ; extra == "dev"
Requires-Dist: pytest (>=8.2.2,<9.0.0) ; extra == "dev"
Requires-Dist: pytest-aiohttp (>=1.0.5,<2.0.0) ; extra == "dev"
Requires-Dist: pytest-asyncio (>=0.23.7,<1.0.0) ; extra == "dev"
Requires-Dist: pytest-cov (>=4.0.0,<5.0.0) ; extra == "dev"
Requires-Dist: requests (>=2.31.0,<3.0.0)
Requires-Dist: requests-mock (>=1.12.1,<2.0.0) ; extra == "dev"
Project-URL: Homepage, https://github.com/No0key/apichainer
Project-URL: Issues, https://github.com/No0key/apichainer/issues
Project-URL: Repository, https://github.com/No0key/apichainer
